VersaLog/__init__.py
VersaLog/logger.py
versalog-1.6.5.dist-info/LICENSE
versalog-1.6.5.dist-info/METADATA
versalog-1.6.5.dist-info/WHEEL
versalog-1.6.5.dist-info/top_level.txt
versalog-1.6.5.dist-info/RECORD
